scalign_umap/__init__.py
scalign_umap/aligned_umap.py
scalign_umap/distances.py
scalign_umap/layouts.py
scalign_umap/parametric_umap.py
scalign_umap/sparse.py
scalign_umap/spectral.py
scalign_umap/umap_.py
scalign_umap/utils.py
scalign_umap/validation.py
scalign_umap-0.2.0.dist-info/METADATA
scalign_umap-0.2.0.dist-info/WHEEL
scalign_umap-0.2.0.dist-info/top_level.txt
scalign_umap-0.2.0.dist-info/RECORD
